Metadata-Version: 2.1
Name: my-dash-component
Version: 0.0.1
Summary: Project Description
Home-page: UNKNOWN
Author: baihe <baihe@xiaomai5.com>
License: MIT
Platform: UNKNOWN
Classifier: Framework :: Dash
License-File: LICENSE
